{
  "project_info": {
    "project_number": "534741161899",
    "project_id": "firebase-aodia"
  },
  "client": [
    {
      "client_info": {
        "mobilesdk_app_id": "1:534741161899:android:4ee8eb8bf41e4876",
        "android_client_info": {
          "package_name": "com.kamelong.aodia"
        }
      },
      "oauth_client": [],
      "api_key": [
        {
          "current_key": "AIzaSyAA2c8HvbGLj2J1isc14SJxq-kXlmblpxo"
        }
      ],
      "services": {
        "analytics_service": {
          "status": 2,
          "analytics_property": {
            "tracking_id": "UA-91963946-1"
          }
        },
        "appinvite_service": {
          "status": 1,
          "other_platform_oauth_client": []
        },
        "ads_service": {
          "status": 1
        }
      }
    }
  ],
  "configuration_version": "1"
}